[
  {
    "full_name": "vercel/platforms",
    "stargazers_count": 2324,
    "open_issues_count": 17,
    "forks_count": 220
  },
  {
    "full_name": "jxnblk/mdx-deck",
    "stargazers_count": 11011,
    "open_issues_count": 145,
    "forks_count": 664
  },
  {
    "full_name": "firstcontributions/first-contributions",
    "stargazers_count": 30784,
    "open_issues_count": 514,
    "forks_count": 55551
  },
  {
    "full_name": "lydiahallie/javascript-questions",
    "stargazers_count": 51078,
    "open_issues_count": 86,
    "forks_count": 7208
  },
  {
    "full_name": "vercel/next.js",
    "stargazers_count": 98619,
    "open_issues_count": 1483,
    "forks_count": 21874
  },
  {
    "full_name": "nrwl/nx",
    "stargazers_count": 15950,
    "open_issues_count": 756,
    "forks_count": 1578
  },
  {
    "full_name": "10up/10up-toolkit",
    "stargazers_count": 59,
    "open_issues_count": 14,
    "forks_count": 15
  },
  {
    "full_name": "responsively-org/responsively-app",
    "stargazers_count": 18713,
    "open_issues_count": 135,
    "forks_count": 817
  },
  {
    "full_name": "public-apis/public-apis",
    "stargazers_count": 223002,
    "open_issues_count": 115,
    "forks_count": 25463
  },
  {
    "full_name": "VSCodium/vscodium",
    "stargazers_count": 18777,
    "open_issues_count": 95,
    "forks_count": 789
  },
  {
    "full_name": "Kong/insomnia",
    "stargazers_count": 25852,
    "open_issues_count": 457,
    "forks_count": 1387
  },
  {
    "full_name": "emmanuellesoy/curso-platzi-react-avanzado",
    "stargazers_count": 1,
    "open_issues_count": 0,
    "forks_count": 0
  },
  {
    "full_name": "tinacms/tinacms",
    "stargazers_count": 8257,
    "open_issues_count": 56,
    "forks_count": 424
  },
  {
    "full_name": "styled-components/styled-components",
    "stargazers_count": 38009,
    "open_issues_count": 142,
    "forks_count": 2385
  },
  {
    "full_name": "facebook/create-react-app",
    "stargazers_count": 98442,
    "open_issues_count": 1899,
    "forks_count": 25795
  },
  {
    "full_name": "joshwcomeau/guppy",
    "stargazers_count": 3255,
    "open_issues_count": 78,
    "forks_count": 171
  },
  {
    "full_name": "facebook/react",
    "stargazers_count": 200026,
    "open_issues_count": 1143,
    "forks_count": 41531
  },
  {
    "full_name": "Semantic-Org/Semantic-UI-React",
    "stargazers_count": 12948,
    "open_issues_count": 183,
    "forks_count": 4001
  },
  {
    "full_name": "gatsbyjs/gatsby",
    "stargazers_count": 53982,
    "open_issues_count": 133,
    "forks_count": 10502
  },
  {
    "full_name": "storybookjs/storybook",
    "stargazers_count": 75826,
    "open_issues_count": 2221,
    "forks_count": 8035
  }
]